pytaifex/__init__.py
pytaifex/py.typed
pytaifex-1.0.0.dist-info/METADATA
pytaifex-1.0.0.dist-info/WHEEL
pytaifex-1.0.0.dist-info/licenses/LICENSE
pytaifex-1.0.0.dist-info/RECORD
