Metadata-Version: 2.4
Name: pytaifex
Version: 1.0.0
Summary: A Python wrapper for the official TTB API of the Taiwan Futures Exchange (TAIFEX).
Author-email: pytree <houjunqimail@gmail.com>
License-File: LICENSE
Requires-Python: >=3.13
Requires-Dist: requests>=2.32.3
Requires-Dist: zmq>=0.0.0
